setup.py
UncleCTowelStuff.egg-info/PKG-INFO
UncleCTowelStuff.egg-info/SOURCES.txt
UncleCTowelStuff.egg-info/dependency_links.txt
UncleCTowelStuff.egg-info/top_level.txt
towelstuff/__init__.py