Metadata-Version: 1.0
Name: UncleCTowelStuff
Version: 0.4.dev0
Summary: UNKNOWN
Home-page: UNKNOWN
Author: UNKNOWN
Author-email: UNKNOWN
License: Creative Commons Attribution-Noncommercial-Share Alike license
Platform: UNKNOWN
